openctp_ctp_debug/thostmduserapi.py
openctp_ctp_debug/thosttraderapi.py
openctp_ctp_debug/_thostmduserapi.pyd
openctp_ctp_debug/_thosttraderapi.pyd
openctp_ctp_debug/__init__.py
openctp_ctp_debug-6.7.2.0.dist-info/DELVEWHEEL
openctp_ctp_debug-6.7.2.0.dist-info/LICENSE
openctp_ctp_debug-6.7.2.0.dist-info/METADATA
openctp_ctp_debug-6.7.2.0.dist-info/RECORD
openctp_ctp_debug-6.7.2.0.dist-info/top_level.txt
openctp_ctp_debug-6.7.2.0.dist-info/WHEEL
openctp_ctp_debug.libs/.load-order-openctp_ctp_debug-6.7.2.0
openctp_ctp_debug.libs/msvcp140-b3ed375e056c79ab0da6fa15f67f8482.dll
openctp_ctp_debug.libs/thostmduserapi_se-913a75e299cf47a2e1dc52fa68173eb5.dll
openctp_ctp_debug.libs/thosttraderapi_se-6e3ddfa14e5bdebd53e3d55dff401ea4.dll
openctp_ctp_debug.libs/vcruntime140_1-05fb2d451f4c5919735e398f6a29473c.dll
