Metadata-Version: 2.1
Name: openctp-ctp-debug
Version: 6.7.2.0
Summary: A package for CTPAPI
Home-page: https://github.com/openctp/openctp-ctp-python
Author: Jedore
Author-email: jedorefight@gmail.com
License: BSD-3-Clause
Keywords: openctp,ctp,ctpapi,trading,investment
Classifier: License :: OSI Approved :: BSD License
Classifier: Programming Language :: Python :: 3
Classifier: Programming Language :: Python :: 3.7
Classifier: Programming Language :: Python :: 3.8
Classifier: Programming Language :: Python :: 3.9
Classifier: Programming Language :: Python :: 3.10
Classifier: Programming Language :: Python :: 3.11
Classifier: Programming Language :: Python :: 3.12
Classifier: Programming Language :: Python :: Implementation :: CPython
Classifier: Operating System :: Microsoft :: Windows
Classifier: Operating System :: POSIX :: Linux
Classifier: Operating System :: MacOS
Classifier: Natural Language :: Chinese (Simplified)
Classifier: Topic :: Office/Business :: Financial :: Investment
Requires-Python: >=3.7
License-File: LICENSE
